rtl/axi_lite_slave.v
`timescale 1ns / 1ps
module axi_lite_slave (
    // Global Signals
    input  wire        aclk,
    input  wire        aresetn,

    // Write Address Channel (AW)
    input  wire [3:0]  awaddr,
    input  wire        awvalid,
    output reg         awready,

   
    // Write Data Channel (W)
    input  wire [31:0] wdata,
    input wire [3:0] wstrb,
    input wire wvalid,
      output reg wready,

    // Write Response Channel (B)
    output reg [1:0]   bresp,
    output reg         bvalid,
    input  wire        bready,
    // Read Address Channel (AR)
    input  wire [3:0]  araddr,
    input  wire        arvalid,
    output reg         arready,
    // Read Data Channel (R)
    output reg [31:0]  rdata,
    output reg [1:0]   rresp,
    output reg         rvalid,
    input  wire        rready
);
    reg[31:0] slv_reg0;
    reg[31:0] slv_reg1;
    reg[31:0] slv_reg2;
    reg[31:0] slv_reg3;

    reg[3:0] axi_araddr;

    always @(posedge aclk ) begin
        //f the Reset button is pressed (Active Low), it forces your "Ready" signals to 0
        if(aresetn==0)begin
            awready<=0;
            wready<=0;
        end else begin
            if((awvalid==1) && (awready==0) && (wvalid==1))begin
                awready<=1;
                wready<=1;
            end else begin
                awready<=0;
                wready<=0;
            end
        end
    end
// to store data

always @(posedge aclk ) begin
    if(aresetn==0) begin
        slv_reg0<=0;
        slv_reg1<=0;
        slv_reg2<=0;
        slv_reg3<=0;
    end else begin
        if((awvalid ==1) && (awready==1) && (wready==1) && (wvalid==1)) begin
            case (awaddr[3:2]) // Look at bits 2 and 3 of address Bits [3:2]: These are the Index. 
            //They tell us exactly which register (0, 1, 2, or 3) we are talking to.
            2'b00    :slv_reg0 <= wdata;
            2'b01    :slv_reg1 <= wdata;
            2'b10    :slv_reg2 <= wdata;
            2'b11    :slv_reg3 <= wdata;
                default: begin end
            endcase
        end
    end    
end

// confirmation
 always @(posedge aclk ) begin
    if (aresetn==0) begin
        bvalid <= 0;
        bresp <= 0;
    end else begin
        if(awvalid && awready && wready && wvalid && bvalid ==0) begin
            bvalid <= 1;
            bresp <= 2'b00;
        end else if (bvalid && bready) begin
            bvalid <=0;
        end
    end
    
 end

 //read data
 always @(posedge aclk ) begin
    if (aresetn==0) begin
        arready <= 0;
        axi_araddr <=0;
    end else begin
        if ((arvalid==1) && (arready==0) ) begin
        arready <= 1;
        axi_araddr <= araddr;  
        end else begin
            arready <= 0;
        end
    
    end
 end
always @(posedge aclk ) begin
    if(aresetn==0) begin
        rvalid <= 0;
    end else begin
        if ((arready==0) && (arvalid==1)) begin
            rvalid <= 1;
            rresp <= 0;
            case (araddr[3:2])
              2'b00  :rdata <= slv_reg0;
              2'b01  :rdata <= slv_reg1;
              2'b10  :rdata <= slv_reg2;
              2'b11  :rdata <= slv_reg3;
                default: rdata <= 32'h0;
            endcase
        end else if(rvalid && rready) begin
            rvalid <= 0;
        end
    end
end
endmodule

tb/tb_axi_slave.v
`timescale 1ns / 1ps
module tb_axi_slave();
    reg aclk;
    reg aresetn;

    reg [3:0]  awaddr;
    reg       awvalid;
    wire         awready;

    reg[31:0] wdata;
    reg [3:0] wstrb;
    reg wvalid;
    wire wready;

    wire[1:0]   bresp;
    wire         bvalid;
    reg        bready;

    reg [3:0]  araddr;
    reg        arvalid;
    wire       arready;

    wire [31:0]  rdata;
    wire [1:0]   rresp;
    wire rvalid;
    reg        rready;

    axi_lite_slave uut (
        .aclk(aclk),
        .aresetn(aresetn),

        // Write Address
        .awaddr(awaddr),
        .awvalid(awvalid),
        .awready(awready),

        // Write Data
        .wdata(wdata),
        .wstrb(wstrb),
        .wvalid(wvalid),
        .wready(wready),

        // Write Response
        .bresp(bresp),
        .bvalid(bvalid),
        .bready(bready),

        // Read Address
        .araddr(araddr),
        .arvalid(arvalid),
        .arready(arready),

        // Read Data
        .rdata(rdata),
        .rresp(rresp),
        .rvalid(rvalid),
        .rready(rready)
    );

    initial begin
        $dumpfile("axi_wave_slave.vcd");  
        $dumpvars(0, tb_axi_slave);  
        aclk=0;
        forever #5 aclk=~aclk;
    end
task axi_write;
        input [3:0]  target_addr;
        input [31:0] target_data;
        begin
            awaddr <=target_addr;
            wdata <=target_data;
            wstrb <= 4'b1111;
            awvalid<=1;
            wvalid <=1;
            bready <=0;
            wait((awready && wready) ==1);
            @(posedge aclk); 
            awvalid <= 0;
            wvalid <= 0;   

            wait(bvalid==1);
            @(posedge aclk);
            bready <=1;
            @(posedge aclk);
            bready <=0;

        end
    endtask

    task axi_read;
        input [3:0] target_addr;
        begin
            araddr <= target_addr;
            arvalid <=1;

            wait(arready);
             @(posedge aclk);
            arvalid <=0;

            rready <=1;
            @(posedge aclk);
            wait(rvalid);
            @(posedge aclk);
            rready <=0;
        end
    endtask

    initial begin
        aresetn = 0;
        awvalid = 0;
        wvalid  = 0;
        bready  = 0;
        arvalid = 0;
        rready  = 0;

        #20 aresetn = 1;  
        // Test 1: Write CAFEBABE to Register 0
        $display("Writing CAFEBABE to Address 0...");
        axi_write(4'h0, 32'hCAFEBABE);

        // Test 2: Read from Register 0
        $display("Reading from Address 0...");
        axi_read(4'h0);
        if (rdata == 32'hCAFEBABE) 
            $display("SUCCESS: Read Data matches Written Data!");
        else 
            $display("ERROR: Read %h, expected CAFEBABE", rdata);
        #50;
        $finish;
    end
    
endmodule

axi_wave.vcd
$date
	Fri Jan 16 20:11:02 2026
$end
$version
	Icarus Verilog
$end
$timescale
	1ps
$end
$scope module tb_axi_slave $end
$var wire 1 ! wready $end
$var wire 1 " rvalid $end
$var wire 2 # rresp [1:0] $end
$var wire 32 $ rdata [31:0] $end
$var wire 1 % bvalid $end
$var wire 2 & bresp [1:0] $end
$var wire 1 ' awready $end
$var wire 1 ( arready $end
$var reg 1 ) aclk $end
$var reg 4 * araddr [3:0] $end
$var reg 1 + aresetn $end
$var reg 1 , arvalid $end
$var reg 4 - awaddr [3:0] $end
$var reg 1 . awvalid $end
$var reg 1 / bready $end
$var reg 1 0 rready $end
$var reg 32 1 wdata [31:0] $end
$var reg 4 2 wstrb [3:0] $end
$var reg 1 3 wvalid $end
$scope module uut $end
$var wire 1 ) aclk $end
$var wire 4 4 araddr [3:0] $end
$var wire 1 + aresetn $end
$var wire 1 , arvalid $end
$var wire 4 5 awaddr [3:0] $end
$var wire 1 . awvalid $end
$var wire 1 / bready $end
$var wire 1 0 rready $end
$var wire 32 6 wdata [31:0] $end
$var wire 4 7 wstrb [3:0] $end
$var wire 1 3 wvalid $end
$var reg 1 ( arready $end
$var reg 1 ' awready $end
$var reg 4 8 axi_araddr [3:0] $end
$var reg 2 9 bresp [1:0] $end
$var reg 1 % bvalid $end
$var reg 32 : rdata [31:0] $end
$var reg 2 ; rresp [1:0] $end
$var reg 1 " rvalid $end
$var reg 32 < slv_reg0 [31:0] $end
$var reg 32 = slv_reg1 [31:0] $end
$var reg 32 > slv_reg2 [31:0] $end
$var reg 32 ? slv_reg3 [31:0] $end
$var reg 1 ! wready $end
$upscope $end
$scope task axi_read $end
$var reg 4 @ target_addr [3:0] $end
$upscope $end
$scope task axi_write $end
$var reg 4 A target_addr [3:0] $end
$var reg 32 B target_data [31:0] $end
$upscope $end
$upscope $end
$enddefinitions $end
$comment Show the parameter values. $end
$dumpall
$end
#0
$dumpvars
bx B
bx A
bx @
bx ?
bx >
bx =
bx <
bx ;
bx :
bx 9
bx 8
bx 7
bx 6
bx 5
bx 4
03
bx 2
bx 1
00
0/
0.
bx -
0,
0+
bx *
0)
x(
x'
bx &
x%
bx $
bx #
x"
x!
$end
#5000
0!
0'
b0 ?
b0 >
b0 =
b0 <
b0 &
b0 9
0%
b0 8
0(
0"
1)
#10000
0)
#15000
1)
#20000
13
1.
b1111 2
b1111 7
b11001010111111101011101010111110 1
b11001010111111101011101010111110 6
b0 -
b0 5
0)
b11001010111111101011101010111110 B
b0 A
1+
#25000
1!
1'
1)
#30000
0)
#35000
1%
b11001010111111101011101010111110 <
0!
0'
03
0.
1)
#40000
0)
#45000
1/
1)
#50000
0)
#55000
1,
b0 *
b0 4
0/
0%
b0 @
1)
#60000
0)
#65000
1(
b11001010111111101011101010111110 $
b11001010111111101011101010111110 :
b0 #
b0 ;
1"
1)
#70000
0)
#75000
0(
10
0,
1)
#80000
0)
#85000
0"
1)
#90000
0)
#95000
00
1)
