rtl/axi_lite_master.v
`timescale 1ns/1ps
module  axi_lite_master (
    input wire aclk,
    input wire aresetn,

    input wire INT_AXI_TXN,
    input wire[3:0] tgt_addr,
    input wire[31:0] tgt_data,
    output reg txn_done,
    output reg txn_error,

    output reg[3:0] awaddr,
    input wire awready,
    output reg awvalid,
    
    output reg[31:0] wdata,
    output reg[3:0] wstrb,
    output reg wvalid,
    input wire wready,

    input wire[1:0] bresp,
    input wire bvalid,
    output reg bready,

    output reg[3:0]  araddr,
    input  wire  arready,
    output reg   arvalid,

    input wire [31:0]  rdata,
    input wire [1:0]   rresp,
    input wire rvalid,
    output reg  rready
);


localparam IDLE      = 2'b00;
localparam SEND_ADDR = 2'b01;
localparam SEND_DATA = 2'b10;
localparam WAIT_RESP = 2'b11;

reg [1:0] current_state;
reg [1:0] next_state;
reg error_reg;

always @(posedge aclk or negedge aresetn) begin
    if(aresetn==0)begin
        current_state <= IDLE;
    end else begin
        current_state <= next_state;
    end
end  
always @(*) begin
    case (current_state)
    IDLE    : if (INT_AXI_TXN) begin
                            next_state=SEND_ADDR  ;      
                end else begin
                    next_state =IDLE;
                end
    SEND_ADDR : if(awready)begin
                    next_state=SEND_DATA;
                end else begin
                    next_state=SEND_ADDR;
                end
    SEND_DATA : if(wready)begin
                    next_state=WAIT_RESP;
                end else begin
                    next_state=SEND_DATA;
                end
    WAIT_RESP : if(bvalid)begin
                    next_state=IDLE;
                end else begin
                    next_state=WAIT_RESP;
                end

        default: next_state=IDLE;
    endcase
end  
always @(posedge aclk or negedge aresetn ) begin
    if(aresetn==0) begin
        awvalid <=0;
        wvalid <=0;
        bready <= 0;
        awaddr <= 0;
        wdata  <= 0;
        txn_done  <= 0;
        txn_error <= 0;
    end else begin
    if((current_state==IDLE) && (INT_AXI_TXN==1))begin
        awaddr <= tgt_addr;
        wdata <= tgt_data;
    end
    awvalid <= (next_state == SEND_ADDR);
    wstrb <= 4'b1111;
    wvalid  <= (next_state == SEND_DATA);
    bready  <= (next_state == WAIT_RESP);

    if (current_state == WAIT_RESP && bvalid == 1) begin
            txn_done <= 1;
            if (bresp != 2'b00) txn_error <= 1;
            else txn_error <= 0;
        end else begin
            txn_done <= 0;
            txn_error <= 0;
        end
end
end
endmodule

tb/tb_axi_master.v
`timescale 1ns/1ps
module tb_axi_master ();
    reg aclk;
    reg aresetn;

    reg INT_AXI_TXN;
    reg[3:0] tgt_addr;
    reg[31:0] tgt_data;
    wire txn_done;
    wire txn_error;

    wire[3:0] awaddr;
    reg awready;
    wire awvalid;
    
    wire[31:0] wdata;
    wire[3:0] wstrb;
    wire wvalid;
    reg wready;

    reg[1:0] bresp;
    reg bvalid;
    wire bready;

    wire[3:0]  araddr;
    reg  arready;
    wire   arvalid;

    reg [31:0]  rdata;
    reg [1:0]   rresp;
    reg rvalid;
    wire  rready;

    axi_lite_master uut(
    .aclk(aclk),
    .aresetn(aresetn),

    .INT_AXI_TXN(INT_AXI_TXN),
    .tgt_addr(tgt_addr),
    .tgt_data(tgt_data),
    .txn_done(txn_done),
    .txn_error(txn_error),

    .awaddr(awaddr),
    .awready(awready),
    .awvalid(awvalid),
    
    .wdata(wdata),
    .wstrb(wstrb),
    .wvalid(wvalid),
    .wready(wready),

    .bresp(bresp),
    .bvalid(bvalid),
    .bready(bready),

    .araddr(araddr),
    .arready(arready),
    .arvalid(arvalid),

    .rdata(rdata),
    .rresp(rresp),
    .rvalid(rvalid),
    .rready(rready)

    );

    initial begin
        $dumpfile("axi_waveform_master.vcd"); 
        $dumpvars(0, tb_axi_master);   
    end

   initial begin
    aclk =0;
   end 
   always #5 aclk = ~aclk;

   initial begin
    aresetn=0;
    INT_AXI_TXN=0;
    awready=0;
    wready=0;
    bvalid=0;
    bresp = 2'b00;

    #20;

    aresetn=1;

    #20;

    // set targets
    tgt_addr= 4'b0101;
    tgt_data= 32'hFFFFFFFF;

    INT_AXI_TXN = 1;  
    #10;              
    INT_AXI_TXN = 0; 
    #100;
    $finish;
   end

// Fake Slave Logic 
always @(posedge aclk ) begin
    if(awvalid==1 && awready==0) begin
        awready <=1;
    end else awready <=0;

    if(wvalid==1 && wready==0)begin
        wready <=1;
    end else wready <=0;

    if(wready && wvalid)begin
        bvalid <=1;
    end
    if(bvalid && bready)begin
        bvalid <=0;
    end
    
end


    
endmodule

axi_waveform_master.vcd
$date
	Wed Jan 21 22:46:51 2026
$end
$version
	Icarus Verilog
$end
$timescale
	1ps
$end
$scope module tb_axi_master $end
$var wire 1 ! wvalid $end
$var wire 4 " wstrb [3:0] $end
$var wire 32 # wdata [31:0] $end
$var wire 1 $ txn_error $end
$var wire 1 % txn_done $end
$var wire 1 & rready $end
$var wire 1 ' bready $end
$var wire 1 ( awvalid $end
$var wire 4 ) awaddr [3:0] $end
$var wire 1 * arvalid $end
$var wire 4 + araddr [3:0] $end
$var reg 1 , INT_AXI_TXN $end
$var reg 1 - aclk $end
$var reg 1 . aresetn $end
$var reg 1 / arready $end
$var reg 1 0 awready $end
$var reg 2 1 bresp [1:0] $end
$var reg 1 2 bvalid $end
$var reg 32 3 rdata [31:0] $end
$var reg 2 4 rresp [1:0] $end
$var reg 1 5 rvalid $end
$var reg 4 6 tgt_addr [3:0] $end
$var reg 32 7 tgt_data [31:0] $end
$var reg 1 8 wready $end
$scope module uut $end
$var wire 1 , INT_AXI_TXN $end
$var wire 1 - aclk $end
$var wire 1 . aresetn $end
$var wire 1 / arready $end
$var wire 1 0 awready $end
$var wire 2 9 bresp [1:0] $end
$var wire 1 2 bvalid $end
$var wire 32 : rdata [31:0] $end
$var wire 2 ; rresp [1:0] $end
$var wire 1 5 rvalid $end
$var wire 4 < tgt_addr [3:0] $end
$var wire 32 = tgt_data [31:0] $end
$var wire 1 8 wready $end
$var parameter 2 > IDLE $end
$var parameter 2 ? SEND_ADDR $end
$var parameter 2 @ SEND_DATA $end
$var parameter 2 A WAIT_RESP $end
$var reg 4 B araddr [3:0] $end
$var reg 1 * arvalid $end
$var reg 4 C awaddr [3:0] $end
$var reg 1 ( awvalid $end
$var reg 1 ' bready $end
$var reg 2 D current_state [1:0] $end
$var reg 2 E next_state [1:0] $end
$var reg 1 & rready $end
$var reg 1 % txn_done $end
$var reg 1 $ txn_error $end
$var reg 32 F wdata [31:0] $end
$var reg 4 G wstrb [3:0] $end
$var reg 1 ! wvalid $end
$upscope $end
$upscope $end
$enddefinitions $end
$comment Show the parameter values. $end
$dumpall
b11 A
b10 @
b1 ?
b0 >
$end
#0
$dumpvars
bx G
b0 F
b0 E
b0 D
b0 C
bx B
bx =
bx <
bx ;
bx :
b0 9
08
bx 7
bx 6
x5
bx 4
bx 3
02
b0 1
00
x/
0.
0-
0,
bx +
x*
b0 )
0(
0'
x&
0%
0$
b0 #
bx "
0!
$end
#5000
1-
#10000
0-
#15000
1-
#20000
0-
1.
#25000
b1111 "
b1111 G
1-
#30000
0-
#35000
1-
#40000
b1 E
0-
1,
b11111111111111111111111111111111 7
b11111111111111111111111111111111 =
b101 6
b101 <
#45000
1(
b11111111111111111111111111111111 #
b11111111111111111111111111111111 F
b101 )
b101 C
b1 D
1-
#50000
0-
0,
#55000
b10 E
10
1-
#60000
0-
#65000
1!
0(
b10 D
00
1-
#70000
0-
#75000
b11 E
18
1-
#80000
0-
#85000
b0 E
1'
0!
b11 D
12
08
1-
#90000
0-
#95000
b0 D
1%
0'
02
1-
#100000
0-
#105000
0%
1-
